<?xml version="1.0" encoding="ISO-8859-1"?>

<form>
	<layout>
		<type>ContainerColumns</type>
		<columns>2</columns>
		<column>1</column>
		<column>2</column>
	</layout>
	<container>
		<id>1</id>
		<questions>101,1,2,3,1000,102,4,5,6,7,8,9,1000,103,10,11,12,13,14,1000,104,15,16,17,18,19,20,1000,105,21,1000</questions>
		<layout>columnContainer</layout>
	</container>
	<container>
		<id>2</id>
		<questions>106,22,23,24,25,26,27,28,1000,107,29,30,1000,108,31,32,33,1000,109,34,35,1000,110,36,37,1000</questions>
		<layout>columnContainer</layout>
	</container>
	
	<question>
		<id>1000</id>
		<type>separator</type>
	</question>	
<question>
		<id>1</id>
		<label>BCG </label>
		<type>DD</type>
		<answer>
			<label>Don't know</label>
		</answer>
		<answer>
			<label>No</label>
		</answer>
		<answer>
			<label>Yes</label>
				<follow>51</follow>
		</answer>
</question>
<question>
		<id>2</id>
		<label> OPV -Dose 1 </label>
		<type>DD</type>
		<answer>
			<label>Don't know</label>
		</answer>
		<answer>
			<label>No</label>
		</answer>
		<answer>
			<label>Yes</label>
				<follow>52</follow>
		</answer>
</question>
<question>
		<id>3</id>
		<label> Hepatitis B - Dose 1 </label>
		<type>DD</type>
		<answer>
			<label>Don't know</label>
		</answer>
		<answer>
			<label>No</label>
		</answer>
		<answer>
			<label>Yes</label>
				<follow>53</follow>
		</answer>
</question>

<question>
		<id>4</id>
		<label> OPV + IPV / OPV only - Dose 2 </label>
		<type>DD</type>
		<answer>
			<label>Don't know</label>
		</answer>
		<answer>
			<label>No</label>
		</answer>
		<answer>
			<label>Yes</label>
				<follow>54</follow>
		</answer>
</question>
<question>
		<id>5</id>
		<label> DTPw / DTPa - Dose 1 </label>
		<type>DD</type>
		<answer>
			<label>Don't know</label>
		</answer>
		<answer>
			<label>No</label>
		</answer>
		<answer>
			<label>Yes</label>
				<follow>55</follow>
		</answer>
</question>
<question>
		<id>6</id>
		<label> Hepatitis B - Dose 2 </label>
		<type>DD</type>
		<answer>
			<label>Don't know</label>
		</answer>
		<answer>
			<label>No</label>
		</answer>
		<answer>
			<label>Yes</label>
				<follow>56</follow>
		</answer>
</question>
<question>
		<id>7</id>
		<label> Hib - Dose 1 </label>
		<type>DD</type>
		<answer>
			<label>Don't know</label>
		</answer>
		<answer>
			<label>No</label>
		</answer>
		<answer>
			<label>Yes</label>
				<follow>57</follow>
		</answer>
</question>
<question>
		<id>8</id>
		<label> Pneumococcal conjugate - Dose 1 </label>
		<type>DD</type>
		<answer>
			<label>Don't know</label>
		</answer>
		<answer>
			<label>No</label>
		</answer>
		<answer>
			<label>Yes</label>
				<follow>58</follow>
		</answer>
</question>
<question>
		<id>9</id>
		<label> Rotaviral vaccines - Dose 1 </label>
		<type>DD</type>
		<answer>
			<label>Don't know</label>
		</answer>
		<answer>
			<label>No</label>
		</answer>
		<answer>
			<label>Yes</label>
				<follow>59</follow>
		</answer>
</question>
<question>
		<id>10</id>
		<label> OPV + IPV / OPV - Dose 3 </label>
		<type>DD</type>
		<answer>
			<label>Don't know</label>
		</answer>
		<answer>
			<label>No</label>
		</answer>
		<answer>
			<label>Yes</label>
				<follow>60</follow>
		</answer>
</question>
<question>
		<id>11</id>
		<label> DTPw / DTPa - Dose 2 </label>
		<type>DD</type>
		<answer>
			<label>Don't know</label>
		</answer>
		<answer>
			<label>No</label>
		</answer>
		<answer>
			<label>Yes</label>
				<follow>61</follow>
		</answer>
</question>
<question>
		<id>12</id>
		<label> Hib - Dose 2 </label>
		<type>DD</type>
		<answer>
			<label>Don't know</label>
		</answer>
		<answer>
			<label>No</label>
		</answer>
		<answer>
			<label>Yes</label>
				<follow>62</follow>
		</answer>
</question>
<question>
		<id>13</id>
		<label> Pneumococcal conjugate - Dose 2 </label>
		<type>DD</type>
		<answer>
			<label>Don't know</label>
		</answer>
		<answer>
			<label>No</label>
		</answer>
		<answer>
			<label>Yes</label>
				<follow>63</follow>
		</answer>
</question>
<question>
		<id>14</id>
		<label>  Rotaviral vaccines - Dose 2 </label>
		<type>DD</type>
		<answer>
			<label>Don't know</label>
		</answer>
		<answer>
			<label>No</label>
		</answer>
		<answer>
			<label>Yes</label>
				<follow>64</follow>
		</answer>
</question>
<question>
		<id>15</id>
		<label>  OPV + IPV / OPV - Dose 4  </label>
		<type>DD</type>
		<answer>
			<label>Don't know</label>
		</answer>
		<answer>
			<label>No</label>
		</answer>
		<answer>
			<label>Yes</label>
				<follow>65</follow>
		</answer>
</question>
<question>
		<id>16</id>
		<label>  DTPw / DTPa - Dose 3   </label>
		<type>DD</type>
		<answer>
			<label>Don't know</label>
		</answer>
		<answer>
			<label>No</label>
		</answer>
		<answer>
			<label>Yes</label>
				<follow>66</follow>
		</answer>
</question>
<question>
		<id>17</id>
		<label>  Hepatitis B - Dose 3  </label>
		<type>DD</type>
		<answer>
			<label>Don't know</label>
		</answer>
		<answer>
			<label>No</label>
		</answer>
		<answer>
			<label>Yes</label>
				<follow>67</follow>
		</answer>
</question>
<question>
		<id>18</id>
		<label> Hib - Dose 3 </label>
		<type>DD</type>
		<answer>
			<label>Don't know</label>
		</answer>
		<answer>
			<label>No</label>
		</answer>
		<answer>
			<label>Yes</label>
				<follow>68</follow>
		</answer>
</question>
<question>
		<id>19</id>
		<label> Pneumococcal conjugate - Dose 3 </label>
		<type>DD</type>
		<answer>
			<label>Don't know</label>
		</answer>
		<answer>
			<label>No</label>
		</answer>
		<answer>
			<label>Yes</label>
				<follow>69</follow>
		</answer>
</question>
<question>
		<id>20</id>
		<label> Rotaviral vaccines - Dose 3 </label>
		<type>DD</type>
		<answer>
			<label>Don't know</label>
		</answer>
		<answer>
			<label>No</label>
		</answer>
		<answer>
			<label>Yes</label>
				<follow>70</follow>
		</answer>
</question>
<question>
		<id>21</id>
		<label>Measles</label>
		<type>DD</type>
		<answer>
			<label>Don't know</label>
		</answer>
		<answer>
			<label>No</label>
		</answer>
		<answer>
			<label>Yes</label>
				<follow>71</follow>
		</answer>
</question>
<question>
		<id>22</id>
		<label> OPV + IPV / OPV - Dose 5 </label>
		<type>DD</type>
		<answer>
			<label>Don't know</label>
		</answer>
		<answer>
			<label>No</label>
		</answer>
		<answer>
			<label>Yes</label>
				<follow>72</follow>
		</answer>
</question>
<question>
		<id>23</id>
		<label> DTPw / DTPa - Booster Dose 1 </label>
		<type>DD</type>
		<answer>
			<label>Don't know</label>
		</answer>
		<answer>
			<label>No</label>
		</answer>
		<answer>
			<label>Yes</label>
				<follow>73</follow>
		</answer>
</question>
<question>
		<id>24</id>
		<label> Hib booster </label>
		<type>DD</type>
		<answer>
			<label>Don't know</label>
		</answer>
		<answer>
			<label>No</label>
		</answer>
		<answer>
			<label>Yes</label>
				<follow>74</follow>
		</answer>
</question>
<question>
		<id>25</id>
		<label> MMR - Dose 1 </label>
		<type>DD</type>
		<answer>
			<label>Don't know</label>
		</answer>
		<answer>
			<label>No</label>
		</answer>
		<answer>
			<label>Yes</label>
				<follow>75</follow>
		</answer>
</question>
<question>
		<id>26</id>
		<label> Pneumococcal conjugate - Dose 4 </label>
		<type>DD</type>
		<answer>
			<label>Don't know</label>
		</answer>
		<answer>
			<label>No</label>
		</answer>
		<answer>
			<label>Yes</label>
				<follow>76</follow>
		</answer>
</question>
<question>
		<id>27</id>
		<label> Hepatitis A - Dose 1 </label>
		<type>DD</type>
		<answer>
			<label>Don't know</label>
		</answer>
		<answer>
			<label>No</label>
		</answer>
		<answer>
			<label>Yes</label>
				<follow>77</follow>
		</answer>
</question>
<question>
		<id>28</id>
		<label> Varicella </label>
		<type>DD</type>
		<answer>
			<label>Don't know</label>
		</answer>
		<answer>
			<label>No</label>
		</answer>
		<answer>
			<label>Yes</label>
				<follow>78</follow>
		</answer>
</question>
<question>
		<id>29</id>
		<label> Diphtherea+Typhoid </label>
		<type>DD</type>
		<answer>
			<label>Don't know</label>
		</answer>
		<answer>
			<label>No</label>
		</answer>
		<answer>
			<label>Yes</label>
				<follow>79</follow>
		</answer>
</question>
<question>
		<id>30</id>
		<label> Hepatitis A - Dose 2 </label>
		<type>DD</type>
		<answer>
			<label>Don't know</label>
		</answer>
		<answer>
			<label>No</label>
		</answer>
		<answer>
			<label>Yes</label>
				<follow>80</follow>
		</answer>
</question>
<question>
		<id>31</id>
		<label> OPV - Dose 6 </label>
		<type>DD</type>
		<answer>
			<label>Don't know</label>
		</answer>
		<answer>
			<label>No</label>
		</answer>
		<answer>
			<label>Yes</label>
				<follow>81</follow>
		</answer>
</question>
<question>
		<id>32</id>
		<label> DTPw / DTPa - Booster Dose 2 </label>
		<type>DD</type>
		<answer>
			<label>Don't know</label>
		</answer>
		<answer>
			<label>No</label>
		</answer>
		<answer>
			<label>Yes</label>
				<follow>82</follow>
		</answer>
</question>
<question>
		<id>33</id>
		<label> MMR - Dose 2 </label>
		<type>DD</type>
		<answer>
			<label>Don't know</label>
		</answer>
		<answer>
			<label>No</label>
		</answer>
		<answer>
			<label>Yes</label>
				<follow>83</follow>
		</answer>
</question>
<question>
		<id>34</id>
		<label> Tdap </label>
		<type>DD</type>
		<answer>
			<label>Don't know</label>
		</answer>
		<answer>
			<label>No</label>
		</answer>
		<answer>
			<label>Yes</label>
				<follow>84</follow>
		</answer>
</question>
<question>
		<id>35</id>
		<label> HPV </label>
		<type>DD</type>
		<answer>
			<label>Don't know</label>
		</answer>
		<answer>
			<label>No</label>
		</answer>
		<answer>
			<label>Yes</label>
				<follow>85</follow>
		</answer>
</question>
<question>
		<id>36</id>
		<label> Varicella - Dose 1 </label>
		<type>DD</type>
		<answer>
			<label>Don't know</label>
		</answer>
		<answer>
			<label>No</label>
		</answer>
		<answer>
			<label>Yes</label>
				<follow>86</follow>
		</answer>
</question>
<question>
		<id>37</id>
		<label>Varicella - Dose 2</label>
		<type>DD</type>
		<answer>
			<label>Don't know</label>
		</answer>
		<answer>
			<label>No</label>
		</answer>
		<answer>
			<label>Yes</label>
				<follow>87</follow>
		</answer>
</question>

<question>
		<id>101</id>
		<label>Age Due - 0 day</label>
		<type>label</type>
</question>
<question>
		<id>102</id>
		<label>Age Due - 6 week</label>
		<type>label</type>
</question>
<question>
		<id>103</id>
		<label>Age Due - 10 week</label>
		<type>label</type>
</question>
<question>
		<id>104</id>
		<label>Age Due - 14 week</label>
		<type>label</type>
</question>
<question>
		<id>105</id>
		<label>Age Due - 9 month</label>
		<type>label</type>
</question>
<question>
		<id>106</id>
		<label>Age Due - 18 month</label>
		<type>label</type>
</question>
<question>
		<id>107</id>
		<label>Age Due - 2 year</label>
		<type>label</type>
</question>
<question>
		<id>108</id>
		<label>Age Due - 5 year</label>
		<type>label</type>
</question>
<question>
		<id>109</id>
		<label>Age Due - 10 year</label>
		<type>label</type>
</question>
<question>
		<id>110</id>
		<label>Age Due - 13 year</label>
		<type>label</type>
</question>

<question>
		<id>51</id>
		<label>Actual Date</label>
		<type>date</type>
</question>
<question>
		<id>52</id>
		<label>Actual Date</label>
		<type>date</type>
</question>
<question>
		<id>53</id>
		<label>Actual Date</label>
		<type>date</type>
</question>
<question>
		<id>54</id>
		<label>Actual Date</label>
		<type>date</type>
</question>
<question>
		<id>55</id>
		<label>Actual Date</label>
		<type>date</type>
</question>
<question>
		<id>56</id>
		<label>Actual Date</label>
		<type>date</type>
</question>
<question>
		<id>57</id>
		<label>Actual Date</label>
		<type>date</type>
</question>
<question>
		<id>58</id>
		<label>Actual Date</label>
		<type>date</type>
</question>
<question>
		<id>59</id>
		<label>Actual Date</label>
		<type>date</type>
</question>
<question>
		<id>60</id>
		<label>Actual Date</label>
		<type>date</type>
</question>
<question>
		<id>61</id>
		<label>Actual Date</label>
		<type>date</type>
</question>
<question>
		<id>62</id>
		<label>Actual Date</label>
		<type>date</type>
</question>
<question>
		<id>63</id>
		<label>Actual Date</label>
		<type>date</type>
</question>
<question>
		<id>64</id>
		<label>Actual Date</label>
		<type>date</type>
</question>
<question>
		<id>65</id>
		<label>Actual Date</label>
		<type>date</type>
</question>
<question>
		<id>66</id>
		<label>Actual Date</label>
		<type>date</type>
</question>
<question>
		<id>67</id>
		<label>Actual Date</label>
		<type>date</type>
</question>
<question>
		<id>68</id>
		<label>Actual Date</label>
		<type>date</type>
</question>
<question>
		<id>69</id>
		<label>Actual Date</label>
		<type>date</type>
</question>
<question>
		<id>70</id>
		<label>Actual Date</label>
		<type>date</type>
</question>
<question>
		<id>71</id>
		<label>Actual Date</label>
		<type>date</type>
</question>
<question>
		<id>72</id>
		<label>Actual Date</label>
		<type>date</type>
</question>
<question>
		<id>73</id>
		<label>Actual Date</label>
		<type>date</type>
</question>
<question>
		<id>74</id>
		<label>Actual Date</label>
		<type>date</type>
</question>
<question>
		<id>75</id>
		<label>Actual Date</label>
		<type>date</type>
</question>
<question>
		<id>76</id>
		<label>Actual Date</label>
		<type>date</type>
</question>
<question>
		<id>77</id>
		<label>Actual Date</label>
		<type>date</type>
</question>
<question>
		<id>78</id>
		<label>Actual Date</label>
		<type>date</type>
</question>
<question>
		<id>79</id>
		<label>Actual Date</label>
		<type>date</type>
</question>
<question>
		<id>80</id>
		<label>Actual Date</label>
		<type>date</type>
</question>
<question>
		<id>81</id>
		<label>Actual Date</label>
		<type>date</type>
</question>
<question>
		<id>82</id>
		<label>Actual Date</label>
		<type>date</type>
</question>
<question>
		<id>83</id>
		<label>Actual Date</label>
		<type>date</type>
</question>
<question>
		<id>84</id>
		<label>Actual Date</label>
		<type>date</type>
</question>
<question>
		<id>85</id>
		<label>Actual Date</label>
		<type>date</type>
</question>
<question>
		<id>86</id>
		<label>Actual Date</label>
		<type>date</type>
</question>
<question>
		<id>87</id>
		<label>Actual Date</label>
		<type>date</type>
</question>
	
</form>
